python_wepay-1.5.0.dist-info/DESCRIPTION.rst
python_wepay-1.5.0.dist-info/metadata.json
python_wepay-1.5.0.dist-info/METADATA
python_wepay-1.5.0.dist-info/pbr.json
python_wepay-1.5.0.dist-info/top_level.txt
python_wepay-1.5.0.dist-info/RECORD
python_wepay-1.5.0.dist-info/WHEEL
wepay/utils.py
wepay/exceptions.py
wepay/api.py
wepay/__init__.py
wepay/tests/test_subscription.py
wepay/tests/test_account.py
wepay/tests/test_withdrawal.py
wepay/tests/test_credit_card.py
wepay/tests/test_api.py
wepay/tests/test_subscription_charge.py
wepay/tests/test_oauth2.py
wepay/tests/__init__.py
wepay/tests/test_app.py
wepay/tests/test_batch.py
wepay/tests/test_checkout.py
wepay/tests/test_subscription_plan.py
wepay/tests/test_user.py
wepay/tests/test_preapproval.py
wepay/calls/credit_card.py
wepay/calls/account.py
wepay/calls/subscription.py
wepay/calls/withdrawal.py
wepay/calls/user.py
wepay/calls/subscription_plan.py
wepay/calls/checkout.py
wepay/calls/__init__.py
wepay/calls/batch.py
wepay/calls/app.py
wepay/calls/base.py
wepay/calls/preapproval.py
wepay/calls/subscription_charge.py
wepay/calls/oauth2.py
build/lib/wepay/utils.py
build/lib/wepay/exceptions.py
build/lib/wepay/api.py
build/lib/wepay/__init__.py
build/lib/wepay/tests/test_subscription.py
build/lib/wepay/tests/test_account.py
build/lib/wepay/tests/test_withdrawal.py
build/lib/wepay/tests/test_credit_card.py
build/lib/wepay/tests/test_api.py
build/lib/wepay/tests/test_subscription_charge.py
build/lib/wepay/tests/test_oauth2.py
build/lib/wepay/tests/__init__.py
build/lib/wepay/tests/test_app.py
build/lib/wepay/tests/test_batch.py
build/lib/wepay/tests/test_checkout.py
build/lib/wepay/tests/test_subscription_plan.py
build/lib/wepay/tests/test_user.py
build/lib/wepay/tests/test_preapproval.py
build/lib/wepay/calls/credit_card.py
build/lib/wepay/calls/account.py
build/lib/wepay/calls/subscription.py
build/lib/wepay/calls/withdrawal.py
build/lib/wepay/calls/user.py
build/lib/wepay/calls/subscription_plan.py
build/lib/wepay/calls/checkout.py
build/lib/wepay/calls/__init__.py
build/lib/wepay/calls/batch.py
build/lib/wepay/calls/app.py
build/lib/wepay/calls/base.py
build/lib/wepay/calls/preapproval.py
