Metadata-Version: 2.0
Name: python-wepay
Version: 1.5.0
Summary: Python SDK for WePay API (third party).
Home-page: https://github.com/lehins/python-wepay
Author: Alexey Kuleshevich
Author-email: lehins@yandex.ru
License: MIT License
Keywords: wepay,payment,credit card
Platform: any
Classifier: Development Status :: 5 - Production/Stable
Classifier: Intended Audience :: Developers
Classifier: License :: OSI Approved :: MIT License
Classifier: Natural Language :: English
Classifier: Operating System :: OS Independent
Classifier: Programming Language :: Python
Classifier: Programming Language :: Python :: 2
Classifier: Programming Language :: Python :: 2.7
Classifier: Programming Language :: Python :: 3
Classifier: Programming Language :: Python :: 3.2
Classifier: Programming Language :: Python :: 3.3
Classifier: Programming Language :: Python :: 3.4
Classifier: Topic :: Software Development :: Libraries :: Python Modules
Requires-Dist: six
